rng_package/__init__.py
rng_package/functions.py
tests/__init__.py
tests/test_cases.py
rng_package-0.1.0.dist-info/LICENSE
rng_package-0.1.0.dist-info/METADATA
rng_package-0.1.0.dist-info/WHEEL
rng_package-0.1.0.dist-info/top_level.txt
rng_package-0.1.0.dist-info/RECORD
